<?xml version="1.0" encoding="utf-8"?>
<Containers>
<Plugin>True</Plugin>
<PluginURL>https://raw.githubusercontent.com/unraid/unraid.patch/main/plugins/unraid.patch.plg</PluginURL>
<PluginAuthor>Lime Technology</PluginAuthor>
<Beta>False</Beta>
<Category>Security: Tools:System</Category>
<Name>Unraid Patch</Name>
<MinVer>6.10.0</MinVer>
<Description>
Keeps your server up to date with the latest patches for the OS</Description>
<Support>https://forums.unraid.net/topic/185560-unraid-patch-plugin/</Support>
<IconFA>asterisk</IconFA>
</Containers>
